vpkg/__init__.py
vpkg-1.0.1.dist-info/METADATA
vpkg-1.0.1.dist-info/WHEEL
vpkg-1.0.1.dist-info/licenses/LICENSE.txt
vpkg-1.0.1.dist-info/RECORD
