Metadata-Version: 2.4
Name: vpkg
Version: 1.0.1
Summary: Vault package designed for use with the Dallas Formula Racing secret vault.
Project-URL: Homepage, https://github.com/DallasFormulaRacing/vpkg
Project-URL: Issues, https://github.com/DallasFormulaRacing/vpkg
Author-email: William Davis <skribbdev@gmail.com>
License-File: LICENSE.txt
Classifier: License :: OSI Approved :: GNU General Public License v3 (GPLv3)
Classifier: Operating System :: OS Independent
Classifier: Programming Language :: Python :: 3
Requires-Python: >=3.0
Requires-Dist: requests
